auto_temp_gpiod_ctrl/__init__.py
auto_temp_gpiod_ctrl/__main__.py
auto_temp_gpiod_ctrl/main.py
auto_temp_gpiod_ctrl/utils/__init__.py
auto_temp_gpiod_ctrl/utils/gpio_control.py
auto_temp_gpiod_ctrl/utils/temps_monitor.py
auto_temp_gpiod_ctrl-0.1.2.dist-info/licenses/LICENSE
auto_temp_gpiod_ctrl-0.1.2.dist-info/METADATA
auto_temp_gpiod_ctrl-0.1.2.dist-info/WHEEL
auto_temp_gpiod_ctrl-0.1.2.dist-info/entry_points.txt
auto_temp_gpiod_ctrl-0.1.2.dist-info/top_level.txt
auto_temp_gpiod_ctrl-0.1.2.dist-info/RECORD
