Metadata-Version: 2.4
Name: auto-temp-gpiod-ctrl
Version: 0.1.2
Summary: Automatic temperature-based GPIO control for any libgpiod 2.x device.
Author: Anthony
Author-email: Anthony <anthonyma24.development@gmail.com>
License: # See https://github.com/yourusername/orange-pi-zero-auto-temp-ctrl
Requires-Python: >=3.7
License-File: LICENSE
Requires-Dist: psutil
Requires-Dist: gpiod>=2.0
Dynamic: author
Dynamic: license-file
Dynamic: requires-python
